<?xml version="1.0" encoding="iso-8859-1"?>
<ClockSkins>
	<ClockSkin>
		<Info>
			<Name>Nduo Big</Name>
			<author>The SharpEnviro Team</author>
			<Website>http://www.sharpenviro.com/</Website>
			<Info>Big version of Nduo</Info>
			<Version>0.8</Version>
			<Category>Analog</Category>
			<Filter>Big</Filter>
		</Info>
		<Skin>
			<Background>Big\watch_face.png</Background>
			<Overlay>Big\watch_glass.png</Overlay>
			<HandHour>Big\hand_hour.png</HandHour>
			<HandMinute>Big\hand_minute.png</HandMinute>
		</Skin>
		<text>
			<Caption>{Date}</Caption>
			<FontName>Arial</FontName>
			<FontSize>8</FontSize>
			<FontColor>0</FontColor>
			<FontAALevel>0</FontAALevel>
			<FontBold>0</FontBold>
			<XMod>18</XMod>
			<YMod>20</YMod>
		</text>
	</ClockSkin>
</ClockSkins>
